PastebinDecoder/PastebinDecoder.py
PastebinDecoder/__init__.py
PastebinDecoder-1.0.1.dist-info/LICENSE
PastebinDecoder-1.0.1.dist-info/METADATA
PastebinDecoder-1.0.1.dist-info/WHEEL
PastebinDecoder-1.0.1.dist-info/top_level.txt
PastebinDecoder-1.0.1.dist-info/RECORD
