Metadata-Version: 2.1
Name: PastebinDecoder
Version: 1.0.1
Summary: Helper class to decode data in Pastebin Pastes
Home-page: https://github.com/g-clef/PastebinDecoder
Author: Aaron Gee-Clough
Author-email: aaron@g-clef.net
License: UNKNOWN
Project-URL: Bug Tracker, https://github.com/g-clef/PastebinDecoder/issues
Platform: UNKNOWN
Classifier: Programming Language :: Python :: 3
Classifier: License :: OSI Approved :: MIT License
Classifier: Operating System :: OS Independent
Requires-Python: >=3.6
Requires-Dist: python-magic (>=0.4.18)
